flex_dtk/__init__.py
flex_dtk/_version.py
flex_dtk/datalake.py
flex_dtk/interactive.py
flex_dtk/py.typed
flex_dtk/trading_db.py
flex_dtk/warehouse.py
flex_dtk-0.5.0.dist-info/licenses/LICENSE
flex_dtk-0.5.0.dist-info/WHEEL
flex_dtk-0.5.0.dist-info/METADATA
flex_dtk-0.5.0.dist-info/RECORD
