Metadata-Version: 2.4
Name: flex-dtk
Version: 0.5.0
Summary: Handy tools for datalake access
Requires-Python: >= 3.9
License-File: LICENSE
Requires-Dist: pandas>=2
Requires-Dist: adlfs>=2023
Requires-Dist: fsspec>=2023
Requires-Dist: pyarrow>=14
Requires-Dist: sqlalchemy>=2
Requires-Dist: pyodbc>=4
Requires-Dist: azure-identity>=1
Requires-Dist: psycopg2-binary>=2
Requires-Dist: ipython>=7 ; extra == "interactive"
Requires-Dist: notebook>=7 ; extra == "interactive"
Requires-Dist: duckdb>=1 ; extra == "interactive"
Provides-Extra: interactive
